consoleTools/__init__.py
consoleTools/core.py
Console_Tools-0.2.1.dist-info/LICENSE
Console_Tools-0.2.1.dist-info/METADATA
Console_Tools-0.2.1.dist-info/WHEEL
Console_Tools-0.2.1.dist-info/top_level.txt
Console_Tools-0.2.1.dist-info/RECORD
