Metadata-Version: 2.1
Name: Console-Tools
Version: 0.2.1
Summary: A fancy text and logging tool for console applications
Home-page: https://github.com/dudeisbrendan03/consoleTools
Author: Brendan T D. Jennings
Author-email: jbrendan70@outlook.com
License: LICENSE
Platform: UNKNOWN
Classifier: Programming Language :: Python :: 3
Classifier: License :: OSI Approved :: GNU General Public License v3 or later (GPLv3+)
Classifier: Operating System :: OS Independent
Requires-Dist: termcolor
Requires-Dist: colorama
